[
  {
    "full_name": "tarunvelli/rails-tabler-starter",
    "stargazers_count": 105,
    "open_issues_count": 0,
    "forks_count": 11
  },
  {
    "full_name": "mcassano/teetimes",
    "stargazers_count": 1,
    "open_issues_count": 0,
    "forks_count": 0
  },
  {
    "full_name": "zdcthomas/dmux",
    "stargazers_count": 290,
    "open_issues_count": 9,
    "forks_count": 8
  },
  {
    "full_name": "notmarkmiranda/swimming_pools",
    "stargazers_count": 1,
    "open_issues_count": 6,
    "forks_count": 0
  },
  {
    "full_name": "jordansinger/SwiftUI-Kit",
    "stargazers_count": 2235,
    "open_issues_count": 5,
    "forks_count": 148
  },
  {
    "full_name": "kuglee/TermiWatch",
    "stargazers_count": 2065,
    "open_issues_count": 49,
    "forks_count": 166
  },
  {
    "full_name": "toolkit-for-ynab/toolkit-for-ynab",
    "stargazers_count": 1395,
    "open_issues_count": 260,
    "forks_count": 342
  },
  {
    "full_name": "toolkit-for-ynab/toolkit-for-ynab.github.io",
    "stargazers_count": 3,
    "open_issues_count": 4,
    "forks_count": 2
  },
  {
    "full_name": "jorgebucaran/hyperapp",
    "stargazers_count": 19017,
    "open_issues_count": 10,
    "forks_count": 872
  },
  {
    "full_name": "kristindiannefoss/little_shop",
    "stargazers_count": 1,
    "open_issues_count": 4,
    "forks_count": 0
  }
]